tests/__init__.py
tests/test_docker_automated.py
tests/test_docker_manager.py
rolypoly-0.2.dist-info/METADATA
rolypoly-0.2.dist-info/WHEEL
rolypoly-0.2.dist-info/entry_points.txt
rolypoly-0.2.dist-info/top_level.txt
rolypoly-0.2.dist-info/RECORD
