Metadata-Version: 2.1
Name: rolypoly
Version: 0.2
Summary: A Docker image rollback tool
Home-page: https://github.com/greedydurian/rolypoly
Author: greedydurian
Requires-Dist: docker
